renkugraphvis/__init__.py
renkugraphvis/config.py
renkugraphvis/graph_utils.py
renkugraphvis/io_utils.py
renkugraphvis/javascript_graph_utils.py
renkugraphvis/plugin.py
renkugraphvis/configs_dir/oda_graph_graphical_config.json
renkugraphvis/configs_dir/oda_graph_nodes_subset_config.json
renkugraphvis/configs_dir/oda_graph_reduction_config.json
renkugraphvis/configs_dir/renku_graph_graphical_config.json
renkugraphvis/configs_dir/renku_graph_reduction_config.json
renkugraphvis/icons/graph_icon.svg
renku_graph_vis-0.0.4.dist-info/METADATA
renku_graph_vis-0.0.4.dist-info/WHEEL
renku_graph_vis-0.0.4.dist-info/entry_points.txt
renku_graph_vis-0.0.4.dist-info/top_level.txt
renku_graph_vis-0.0.4.dist-info/RECORD
